devpipe/__init__.py
devpipe/config.py
devpipe/core/__init__.py
devpipe/core/_commons.py
devpipe/core/metadata.py
devpipe/core/pipeline.py
devpipe/core/step.py
devpipe/database.py
devpipe/logger.py
devpipe/models/__init__.py
devpipe/models/base.py
devpipe/models/links.py
devpipe/models/pipeline.py
devpipe/models/step.py
devpipe/storage/__init__.py
devpipe/storage/local.py
devpipe-0.1.0.dist-info/LICENSE
devpipe-0.1.0.dist-info/METADATA
devpipe-0.1.0.dist-info/WHEEL
devpipe-0.1.0.dist-info/RECORD
